{"collections": [{"collection": "pov-edition-one", "name": "POV Edition One", "description": "", "image_url": "https://i.seadn.io/s/raw/files/5b689b9b0a0f0d28082d3e95f999c48c.jpg?w=500&auto=format", "banner_image_url": "", "owner": "0x8ca3df3ec0cf9f1b16023ba3e12af982450718dc", "safelist_status": "not_requested", "category": "", "is_disabled": false, "is_nsfw": false, "trait_offers_enabled": false, "collection_offers_enabled": true, "opensea_url": "https://opensea.io/collection/pov-edition-one", "project_url": "", "wiki_url": "", "discord_url": "", "telegram_url": "", "twitter_username": "", "instagram_username": "", "contracts": [{"address": "0x19589f7cc921522b8740a0880fdeb00e5d8b76b0", "chain": "ethereum"}]}, {"collection": "certificates-of-authenticity-3", "name": "Certificates of Authenticity", "description": "These are certificates of authenticity that accompany physical art. ", "image_url": "https://i.seadn.io/s/raw/files/ce9dc5de7db160174124d5acb09b7699.jpg?w=500&auto=format", "banner_image_url": "", "owner": "0x937168b9cb24322c3bad389e3ddde2b99b1a2c82", "safelist_status": "not_requested", "category": "art", "is_disabled": false, "is_nsfw": false, "trait_offers_enabled": false, "collection_offers_enabled": true, "opensea_url": "https://opensea.io/collection/certificates-of-authenticity-3", "project_url": "", "wiki_url": "", "discord_url": "", "telegram_url": "", "twitter_username": "", "instagram_username": "", "contracts": [{"address": "0xa497d1f88453379933c481c7095dbcb448f17e7b", "chain": "ethereum"}]}, {"collection": "karma-llamacatacorn", "name": "Karma-Llamacatacorn", "description": "", "image_url": "https://i.seadn.io/s/raw/files/8b48c60036436eab9b90d273c7516bf2.jpg?w=500&auto=format", "banner_image_url": "", "owner": "0xb17dfb2b9a30a6e623eca68022e20a311820f537", "safelist_status": "not_requested", "category": "art", "is_disabled": false, "is_nsfw": false, "trait_offers_enabled": false, "collection_offers_enabled": true, "opensea_url": "https://opensea.io/collection/karma-llamacatacorn", "project_url": "", "wiki_url": "", "discord_url": "", "telegram_url": "", "twitter_username": "", "instagram_username": "", "contracts": [{"address": "0x5732225daf8dc6dcdabed2e0ce6796128a2958e0", "chain": "ethereum"}]}, {"collection": "80m", "name": "80m", "description": "", "image_url": "https://i.seadn.io/s/raw/files/9be968f1e03e4525fa344c4e2c6671f8.png?w=500&auto=format", "banner_image_url": "", "owner": "0xcf899489ad9344ce168c4d239152387f241bcccc", "safelist_status": "not_requested", "category": "", "is_disabled": false, "is_nsfw": false, "trait_offers_enabled": false, "collection_offers_enabled": true, "opensea_url": "https://opensea.io/collection/80m", "project_url": "", "wiki_url": "", "discord_url": "", "telegram_url": "", "twitter_username": "", "instagram_username": "", "contracts": [{"address": "0xcfebad9c4fe5ea364f50af7d81ed55fbb2c20545", "chain": "ethereum"}]}, {"collection": "illustration-102", "name": "illustration", "description": "We create a variety of unique art.", "image_url": "https://i.seadn.io/s/raw/files/7aa61ecdb5f9a4e076501224547373ff.png?w=500&auto=format", "banner_image_url": "https://i.seadn.io/s/primary-drops/0xc1aa57ee3c18c3053d7fc0312c8e6c6e32c80092/34317297:about:media:3930f13c-ff94-46bc-bdc0-8f5236b893c4.png?w=500&auto=format", "owner": "0x1265855ad6c0b083a721f59caefe49740575b2a3", "safelist_status": "not_requested", "category": "pfps", "is_disabled": false, "is_nsfw": false, "trait_offers_enabled": false, "collection_offers_enabled": true, "opensea_url": "https://opensea.io/collection/illustration-102", "project_url": "", "wiki_url": "", "discord_url": "", "telegram_url": "", "twitter_username": "", "instagram_username": "", "contracts": [{"address": "0xc1aa57ee3c18c3053d7fc0312c8e6c6e32c80092", "chain": "ethereum"}]}, {"collection": "j6-s-workspace-6", "name": "J6's Workspace", "description": "", "image_url": "", "banner_image_url": "", "owner": "0x98a769ce485e8cdbb88ba3761fec683166fffe36", "safelist_status": "not_requested", "category": "", "is_disabled": false, "is_nsfw": false, "trait_offers_enabled": false, "collection_offers_enabled": false, "opensea_url": "https://opensea.io/collection/j6-s-workspace-6", "project_url": "", "wiki_url": "", "discord_url": "", "telegram_url": "", "twitter_username": "", "instagram_username": "", "contracts": [{"address": "0xe8ddf46bd00df04c1491538548ec7973cd108e64", "chain": "ethereum"}]}, {"collection": "j6-s-workspace-5", "name": "J6's Workspace", "description": "", "image_url": "", "banner_image_url": "", "owner": "0x98a769ce485e8cdbb88ba3761fec683166fffe36", "safelist_status": "not_requested", "category": "", "is_disabled": false, "is_nsfw": false, "trait_offers_enabled": false, "collection_offers_enabled": true, "opensea_url": "https://opensea.io/collection/j6-s-workspace-5", "project_url": "", "wiki_url": "", "discord_url": "", "telegram_url": "", "twitter_username": "", "instagram_username": "", "contracts": [{"address": "0x86573612c1b895d333df281b0101c7c30242068a", "chain": "ethereum"}]}, {"collection": "j6-s-workspace-4", "name": "J6's Workspace", "description": "", "image_url": "", "banner_image_url": "", "owner": "0x98a769ce485e8cdbb88ba3761fec683166fffe36", "safelist_status": "not_requested", "category": "", "is_disabled": false, "is_nsfw": false, "trait_offers_enabled": false, "collection_offers_enabled": true, "opensea_url": "https://opensea.io/collection/j6-s-workspace-4", "project_url": "", "wiki_url": "", "discord_url": "", "telegram_url": "", "twitter_username": "", "instagram_username": "", "contracts": [{"address": "0xee082fabbc7589545cca7b98fb3cb752dffec8aa", "chain": "ethereum"}]}, {"collection": "celestial-stride", "name": "Celestial Stride Shoes Collection", "description": "It's a piece of my heart that I hope will bring comfort to someone.\n\nThe shoe is called 'Celestial Stride'.\nIt's a persona shoe that means \u201ca dignified stride as if you're walking on a celestial path, even as you walk on earth.\u201d\n\nIt's a prayer for all those who feel so small and insignificant that they cower in their own shame.\nI hope that in any moment of your life, you remember how precious you are....\nIf my artwork connects hearts and minds, I would be more surprised and happy than that.", "image_url": "https://i.seadn.io/s/raw/files/09cf33e64b41e57376a7681c43bd0b94.png?w=500&auto=format", "banner_image_url": "https://i.seadn.io/s/primary-drops/0x86eea02a85d1842b4eec79b1a44cbef7f57e252f/34317197:about:media:2abb1824-c496-44e6-8e40-7ca2c5046fc5.png?w=500&auto=format", "owner": "0x67ed8eb7cf997d92b44f153b2768485400b8e538", "safelist_status": "not_requested", "category": "art", "is_disabled": false, "is_nsfw": false, "trait_offers_enabled": false, "collection_offers_enabled": false, "opensea_url": "https://opensea.io/collection/celestial-stride", "project_url": "", "wiki_url": "", "discord_url": "", "telegram_url": "", "twitter_username": "", "instagram_username": "", "contracts": [{"address": "0x86eea02a85d1842b4eec79b1a44cbef7f57e252f", "chain": "ethereum"}]}, {"collection": "j6-s-workspace-3", "name": "J6's Workspace", "description": "", "image_url": "", "banner_image_url": "", "owner": "0x98a769ce485e8cdbb88ba3761fec683166fffe36", "safelist_status": "not_requested", "category": "", "is_disabled": false, "is_nsfw": false, "trait_offers_enabled": false, "collection_offers_enabled": false, "opensea_url": "https://opensea.io/collection/j6-s-workspace-3", "project_url": "", "wiki_url": "", "discord_url": "", "telegram_url": "", "twitter_username": "", "instagram_username": "", "contracts": [{"address": "0x1ea7d826c9ebdebe8a5daaa1b28235d2f78a5869", "chain": "ethereum"}]}, {"collection": "j6-s-workspace-2", "name": "J6's Workspace", "description": "", "image_url": "", "banner_image_url": "", "owner": "0x98a769ce485e8cdbb88ba3761fec683166fffe36", "safelist_status": "not_requested", "category": "", "is_disabled": false, "is_nsfw": false, "trait_offers_enabled": false, "collection_offers_enabled": true, "opensea_url": "https://opensea.io/collection/j6-s-workspace-2", "project_url": "", "wiki_url": "", "discord_url": "", "telegram_url": "", "twitter_username": "", "instagram_username": "", "contracts": [{"address": "0x20a11a46e47d749a865955215ba728fc04e72b24", "chain": "ethereum"}]}, {"collection": "j6-s-workspace-1", "name": "J6's Workspace", "description": "", "image_url": "", "banner_image_url": "", "owner": "0x98a769ce485e8cdbb88ba3761fec683166fffe36", "safelist_status": "not_requested", "category": "", "is_disabled": false, "is_nsfw": false, "trait_offers_enabled": false, "collection_offers_enabled": true, "opensea_url": "https://opensea.io/collection/j6-s-workspace-1", "project_url": "", "wiki_url": "", "discord_url": "", "telegram_url": "", "twitter_username": "", "instagram_username": "", "contracts": [{"address": "0x631516d7659c4b62e4460a45886bef63e76c138f", "chain": "ethereum"}]}, {"collection": "lazymoonie", "name": "Lazy Moonie", "description": "Hello! Artice Factory's here \ud83e\udd70\n\nLazy Moonie is our latest projects from our 11 years old artist. We will periodically upload items that are part of this project. ", "image_url": "https://i.seadn.io/s/raw/files/4fde44985c58ae7113b25db161af3a32.jpg?w=500&auto=format", "banner_image_url": "https://i.seadn.io/s/primary-drops/0xc24aad76b146adec386320f2f68bfa146211b5b1/34317140:about:media:22bce0b1-5b34-46c3-b589-c016ce7d5fe1.png?w=500&auto=format", "owner": "0x6df7072086ef832fd7a6c344a09fcd43b31da147", "safelist_status": "not_requested", "category": "art", "is_disabled": false, "is_nsfw": false, "trait_offers_enabled": false, "collection_offers_enabled": true, "opensea_url": "https://opensea.io/collection/lazymoonie", "project_url": "", "wiki_url": "", "discord_url": "", "telegram_url": "", "twitter_username": "", "instagram_username": "", "contracts": [{"address": "0xc24aad76b146adec386320f2f68bfa146211b5b1", "chain": "ethereum"}]}, {"collection": "indecisive-guy-1", "name": "Indecisive Guy", "description": "He doesn't know what to do.  You have confused him.  You've shut him down.  He's lost.  He's unsure.", "image_url": "https://i.seadn.io/s/raw/files/fec65b24182f4ac766e1bab44e6eda04.gif?w=500&auto=format", "banner_image_url": "", "owner": "0xb6441f2f7571d74eee90a1ebef8c8c676cddc722", "safelist_status": "not_requested", "category": "art", "is_disabled": false, "is_nsfw": false, "trait_offers_enabled": false, "collection_offers_enabled": false, "opensea_url": "https://opensea.io/collection/indecisive-guy-1", "project_url": "", "wiki_url": "", "discord_url": "", "telegram_url": "", "twitter_username": "", "instagram_username": "", "contracts": [{"address": "0xad24e9120184ce1d67cc1365eafda2f202e45293", "chain": "ethereum"}]}, {"collection": "j6-s-workspace", "name": "J6's Workspace", "description": "", "image_url": "https://i.seadn.io/s/raw/files/69b721860b2d2c92f1d3dc27dcf7c733.jpg?w=500&auto=format", "banner_image_url": "", "owner": "0x98a769ce485e8cdbb88ba3761fec683166fffe36", "safelist_status": "not_requested", "category": "", "is_disabled": false, "is_nsfw": false, "trait_offers_enabled": false, "collection_offers_enabled": true, "opensea_url": "https://opensea.io/collection/j6-s-workspace", "project_url": "", "wiki_url": "", "discord_url": "", "telegram_url": "", "twitter_username": "", "instagram_username": "", "contracts": [{"address": "0xc2a4566833bd6079005bf91f5adf873ab50c875b", "chain": "ethereum"}]}, {"collection": "queen-of-mountain-1", "name": "Queen Of Mountain", "description": "", "image_url": "", "banner_image_url": "", "owner": "0x5831533d437c43f7fce75cb3857bbbbdab430341", "safelist_status": "not_requested", "category": "", "is_disabled": false, "is_nsfw": false, "trait_offers_enabled": false, "collection_offers_enabled": true, "opensea_url": "https://opensea.io/collection/queen-of-mountain-1", "project_url": "", "wiki_url": "", "discord_url": "", "telegram_url": "", "twitter_username": "", "instagram_username": "", "contracts": [{"address": "0xbe84aca634f76d7e51eb78ed73c4188be2dfe07d", "chain": "ethereum"}]}, {"collection": "goldbar-2", "name": "GOLDBAR", "description": "A portion of the sales revenue from the gold bar goes to helping local underfed children.", "image_url": "https://i.seadn.io/s/raw/files/6959d42169934baa0e0458886ffb7f7c.jpg?w=500&auto=format", "banner_image_url": "", "owner": "0xdb5ecde9e6ae181aafb3e931fa7a291b906f88f2", "safelist_status": "not_requested", "category": "art", "is_disabled": false, "is_nsfw": false, "trait_offers_enabled": false, "collection_offers_enabled": true, "opensea_url": "https://opensea.io/collection/goldbar-2", "project_url": "https://www.instagram.com/nft_goldmarket?igsh=dmU0dDhtbjRiYnJ1", "wiki_url": "", "discord_url": "", "telegram_url": "", "twitter_username": "", "instagram_username": "", "contracts": [{"address": "0x5e6252d0c658646f9e2a959c555d252e4c8543a3", "chain": "ethereum"}]}, {"collection": "screwhornart", "name": "ScrewHornArt", "description": "", "image_url": "https://i.seadn.io/s/raw/files/ab4204b82dcba16ca37d7e25b401676f.png?w=500&auto=format", "banner_image_url": "", "owner": "0x797398db3fac1f8b8f5be41fa882f530c1328034", "safelist_status": "not_requested", "category": "", "is_disabled": false, "is_nsfw": false, "trait_offers_enabled": false, "collection_offers_enabled": true, "opensea_url": "https://opensea.io/collection/screwhornart", "project_url": "", "wiki_url": "", "discord_url": "", "telegram_url": "", "twitter_username": "", "instagram_username": "", "contracts": [{"address": "0x3b89c968029dffc0f59b3f1bd2a57399b65f3dff", "chain": "ethereum"}]}, {"collection": "aurora-lines", "name": "Aurora Lines", "description": "Lines merging into a radiant aurora that blankets the night sky, blending with the Milky Way and distant galaxies. This cosmic tapestry feels infinite, a bridge between the physical and the metaphysical, reminding us of the profound connection between all things in the universe.\n\n", "image_url": "https://i.seadn.io/s/raw/files/2f6ceae72635d49d1657aa6853b54f3c.png?w=500&auto=format", "banner_image_url": "", "owner": "0xe1c80be2927856d49c15c1760c01080368083f0d", "safelist_status": "not_requested", "category": "art", "is_disabled": false, "is_nsfw": false, "trait_offers_enabled": false, "collection_offers_enabled": true, "opensea_url": "https://opensea.io/collection/aurora-lines", "project_url": "", "wiki_url": "", "discord_url": "", "telegram_url": "", "twitter_username": "", "instagram_username": "", "contracts": [{"address": "0x7a5df996fe2885406cc6922bbd4b95ed9167c4db", "chain": "ethereum"}]}, {"collection": "zardain-2", "name": "Zardain", "description": "", "image_url": "https://i.seadn.io/s/raw/files/517a959f63c47d2e4968d831f2a67df9.jpg?w=500&auto=format", "banner_image_url": "", "owner": "0xfc3773515f9b60b62c37bf6ccea5aec9d66c824d", "safelist_status": "not_requested", "category": "", "is_disabled": false, "is_nsfw": false, "trait_offers_enabled": false, "collection_offers_enabled": true, "opensea_url": "https://opensea.io/collection/zardain-2", "project_url": "", "wiki_url": "", "discord_url": "", "telegram_url": "", "twitter_username": "", "instagram_username": "", "contracts": [{"address": "0xc92fb687325a826dccde3b78a6e482bde920d9f5", "chain": "ethereum"}]}, {"collection": "zardain-1", "name": "Zardain", "description": "", "image_url": "https://i.seadn.io/s/raw/files/3757f8c2c3c649fa5151dcb5cf440bec.jpg?w=500&auto=format", "banner_image_url": "", "owner": "0xfc3773515f9b60b62c37bf6ccea5aec9d66c824d", "safelist_status": "not_requested", "category": "", "is_disabled": false, "is_nsfw": false, "trait_offers_enabled": false, "collection_offers_enabled": true, "opensea_url": "https://opensea.io/collection/zardain-1", "project_url": "", "wiki_url": "", "discord_url": "", "telegram_url": "", "twitter_username": "", "instagram_username": "", "contracts": [{"address": "0xb5547c0afa7584386c92d16e6156f32309164e25", "chain": "ethereum"}]}, {"collection": "magnus-vox", "name": "Magnus Vox", "description": "", "image_url": "https://i.seadn.io/s/raw/files/956c36df013f594f87222bd605f4efb4.png?w=500&auto=format", "banner_image_url": "", "owner": "0x73c533dfacc330a79f7c27524523166f6d9a0cf9", "safelist_status": "not_requested", "category": "", "is_disabled": false, "is_nsfw": false, "trait_offers_enabled": false, "collection_offers_enabled": true, "opensea_url": "https://opensea.io/collection/magnus-vox", "project_url": "", "wiki_url": "", "discord_url": "", "telegram_url": "", "twitter_username": "", "instagram_username": "", "contracts": [{"address": "0x7338513cee4994c54d39bc06911a0be243dc9e36", "chain": "ethereum"}]}, {"collection": "nn-186", "name": "NATURALNUMBERS", "description": "https://opensea.io/assets/ethereum/0xbc84b0590672c422dacb4f609b03b0047b0ab8cd/9/\nhttps://opensea.io/assets/ethereum/0xbc84b0590672c422dacb4f609b03b0047b0ab8cd/5/", "image_url": "https://i.seadn.io/s/raw/files/905ae18a741d9758368b4871c6a61a4f.jpg?w=500&auto=format", "banner_image_url": "https://i.seadn.io/s/primary-drops/0xa0c3fbd0b50e770af61285fa61ebbd3607fd6103/34316509:about:media:1bbfcc33-5390-4eac-b5c0-5e5faf2ad3b8.jpeg?w=500&auto=format", "owner": "0x00029a525efceb364ce594824b12d3565f85a937", "safelist_status": "not_requested", "category": "memberships", "is_disabled": false, "is_nsfw": false, "trait_offers_enabled": false, "collection_offers_enabled": true, "opensea_url": "https://opensea.io/collection/nn-186", "project_url": "https://opensea.io/assets/ethereum/0x1885569df5818167e02feaa2f74b67e67caf23f1/2/", "wiki_url": "", "discord_url": "", "telegram_url": "", "twitter_username": "", "instagram_username": "", "contracts": [{"address": "0xa0c3fbd0b50e770af61285fa61ebbd3607fd6103", "chain": "ethereum"}]}, {"collection": "traversing-mediums", "name": "Traversing Mediums", "description": "", "image_url": "https://i.seadn.io/s/raw/files/54f81b6da2a7d547379121ff6e2dd504.jpg?w=500&auto=format", "banner_image_url": "", "owner": "0x12cd79a1670397f07dc91eebecad62809c9a4204", "safelist_status": "not_requested", "category": "", "is_disabled": false, "is_nsfw": false, "trait_offers_enabled": false, "collection_offers_enabled": true, "opensea_url": "https://opensea.io/collection/traversing-mediums", "project_url": "", "wiki_url": "", "discord_url": "", "telegram_url": "", "twitter_username": "", "instagram_username": "", "contracts": [{"address": "0x26b5810242e1f89a97cf24927d33d087b69d1086", "chain": "ethereum"}]}, {"collection": "don-quixote-anniversary", "name": "Don Quixote anniversary", "description": "", "image_url": "https://i.seadn.io/s/raw/files/cf41687562657132e20ceac677f8a82c.jpg?w=500&auto=format", "banner_image_url": "", "owner": "0xf13b6539b0b311c346b2739884ba896c8b92396f", "safelist_status": "not_requested", "category": "", "is_disabled": false, "is_nsfw": false, "trait_offers_enabled": false, "collection_offers_enabled": true, "opensea_url": "https://opensea.io/collection/don-quixote-anniversary", "project_url": "", "wiki_url": "", "discord_url": "", "telegram_url": "", "twitter_username": "", "instagram_username": "", "contracts": [{"address": "0x3f0d73f37ecf84ef67c4f2b6a2894974868d68f9", "chain": "ethereum"}]}, {"collection": "rock-orient-foundation-rwa", "name": "Rock Orient Foundation/RWA", "description": "Leveraging the power of blockchain technology, we can now create secure NFT representations of Real World Assets (RWA), such as physical art pieces.\nBy bridging the physical and digital worlds, NFT-linked assets provide collectors, artists, and investors with new opportunities for mutual growth. This approach enhances trust and transparency in the art market, offering long-term security and flexibility.\n\nWhether for high-value artwork or emerging pieces, NFT representations open doors to new revenue streams, global visibility, and innovative ways to engage with the evolving art economy.\n\nThrough this partnership, we aim to elevate our clients\u2019 missions, unlock new revenue opportunities, and foster global cultural appreciation, all while maintaining artistic integrity.", "image_url": "https://i.seadn.io/s/raw/files/2e3bd7df2a3af7bc6aeb547392147e34.jpg?w=500&auto=format", "banner_image_url": "", "owner": "0x59f834c8ad3c70e7d4702578f2dea5e2e3248a08", "safelist_status": "not_requested", "category": "art", "is_disabled": false, "is_nsfw": false, "trait_offers_enabled": false, "collection_offers_enabled": true, "opensea_url": "https://opensea.io/collection/rock-orient-foundation-rwa", "project_url": "", "wiki_url": "", "discord_url": "", "telegram_url": "", "twitter_username": "", "instagram_username": "", "contracts": [{"address": "0x8f2893039acff3a9049ee53da414b329572c7c5b", "chain": "ethereum"}]}, {"collection": "caishenyeh", "name": "CSYF", "description": "Cai Shen Yeh Fashion (CSYF) \r\nIntroduction\r\nCai Shen Yeh Fashion (CSYF) is the next evolution of digital fashion NFTs, extending from the original Cai Shen Yeh (CSY) NFT collection. CSYF redefines NFT utility by offering a fashion-centric, open platform where freelancers, designers, and artists can easily create, sell, and rebrand their own NFT-based fashion illustrations.\r\nCSYF is designed to be a decentralized, limitless, and creator-friendly NFT ecosystem, where artists and NFT holders can freely transform designs into new interpretations while maintaining ownership and creative control.", "image_url": "https://i.seadn.io/s/raw/files/a936a50ef95999f043e1f98c0b4e1e43.jpg?w=500&auto=format", "banner_image_url": "https://i.seadn.io/s/primary-drops/0xcf3b144b4fd5085fdd74f05eef841a9dec72906a/34316203:about:media:c19db8c8-6d47-4d60-81ea-3223c49b7634.jpeg?w=500&auto=format", "owner": "0x612a6591f260e1f5b31e99e8587098661c1c6b6e", "safelist_status": "not_requested", "category": "art", "is_disabled": false, "is_nsfw": false, "trait_offers_enabled": false, "collection_offers_enabled": true, "opensea_url": "https://opensea.io/collection/caishenyeh", "project_url": "", "wiki_url": "", "discord_url": "", "telegram_url": "", "twitter_username": "caiyeh81382", "instagram_username": "", "contracts": [{"address": "0xcf3b144b4fd5085fdd74f05eef841a9dec72906a", "chain": "ethereum"}]}, {"collection": "caishenyeh-fashion", "name": "CAISHENYEH FASHION", "description": "", "image_url": "https://i.seadn.io/s/raw/files/a936a50ef95999f043e1f98c0b4e1e43.jpg?w=500&auto=format", "banner_image_url": "", "owner": "0x612a6591f260e1f5b31e99e8587098661c1c6b6e", "safelist_status": "not_requested", "category": "", "is_disabled": false, "is_nsfw": false, "trait_offers_enabled": false, "collection_offers_enabled": true, "opensea_url": "https://opensea.io/collection/caishenyeh-fashion", "project_url": "", "wiki_url": "", "discord_url": "", "telegram_url": "", "twitter_username": "", "instagram_username": "", "contracts": [{"address": "0x92e5808a49369f5a1d2983000010174696887196", "chain": "ethereum"}]}, {"collection": "ab-signature-author-2", "name": "AB SIGNATURE AUTHOR", "description": "REINVENTED ORTHODOX CHURCH / A REAL ASSET", "image_url": "https://i.seadn.io/s/raw/files/10a3298037bfa4d019fbd889c1c3275b.jpg?w=500&auto=format", "banner_image_url": "https://i.seadn.io/s/primary-drops/0x541d6ebc6f04d94753b4cbe3714b94de4d127df4/34316177:about:media:813f5107-f71e-4321-bce3-b3faeb258e21.png?w=500&auto=format", "owner": "0x7d609ec6b83d7dd29cdc531bc43a0def01246e14", "safelist_status": "not_requested", "category": "virtual-worlds", "is_disabled": false, "is_nsfw": false, "trait_offers_enabled": true, "collection_offers_enabled": true, "opensea_url": "https://opensea.io/collection/ab-signature-author-2", "project_url": "https://www.abandpartners.net", "wiki_url": "", "discord_url": "", "telegram_url": "", "twitter_username": "Alexandrin_B", "instagram_username": "", "contracts": [{"address": "0x541d6ebc6f04d94753b4cbe3714b94de4d127df4", "chain": "ethereum"}]}, {"collection": "blockchain-fart-gang", "name": "Blockchain Fart Gang", "description": "You\u2019ve heard of the blockchain. You know all about Cryptocurrency. You\u2019ve seen NFTs. But do you know the real secret behind the system? No, we\u2019re not talking about Satoshi Nakamoto, the secret creator of Bitcoin. We\u2019re talking about something far bigger. It's a secret that would make you gag\u2026 quite literally.\nLet us introduce you to the Blockchain Fart Gang! A team of brave, yet smelly soldiers dedicated to keeping the blockchain safe from the enemies of Crypto. No one knows where the Blockchain Fart Gang came from or how they formed. All we know is they have severe IBS and gastrointestinal problems. Normally, this would be an absolute nightmare to deal with, but the Blockchain Fart Gang have found a way to harness their gas for good! You see, the Blockchain Fart Gang are far more than their IBS tummies may seem. They are genius-level rocket scientists too! Over the last two years, they have developed a very advanced science that allows them to build rockets capable of shrinking to a near subatomic size which are flown straight into the blockchain to specifically hunt down bad characters and force them out of the blockchain nodes. They call them\u2026 the Smart Fart Rockets!\nThe mixture of the rocket's flames along with Blockchain Fart Gang farts creates an explosion so intense, fiery, and smelly that no bad characters could ever stick around. That\u2019s a very powerful fart indeed!\nThe Blockchain Fart Gang monitors the blockchain 24 hours a day, 365 days a year \u2013 with no exceptions. But staying away for that long requires a lot of energy. Energy drinks, ice cream, milkshakes, beans, veggies and more. Of course, none of it agrees with their stomachs though. Our experts have found that when a Blockchain Fart Gang member drinks an energy drink, for example, they emit a foul red, smoky stench. Each food and drink appears to create different smells with different colored smoke. But the BFG needs your help. Building all these rockets is expensive, not to mention the constant supply of gas-inducing food! The Blockchain Fart Gang needs funding to keep the bad characters away from our safe Crypto investments. That\u2019s where you come in!\nThe Blockchain Fart Gang is now releasing its very own NFT collection to celebrate all the amazing, gassy work they do on the blockchain. You can spot a BFG character from their trademark cocked leg, primed to let out a devastating fart. Each NFT comes with its smoke color, depending on what the BFG member had for breakfast that morning. Some show the rockets primed to blow, while others show the aftermath, bad characters and all.\nEvery Blockchain Fart Gang NFT comes with commercial rights and is digitally drawn, producing the most beautiful farts to grace the Blockchain and the most unique art to grace your NFT collection. \nWelcome to the Blockchain Fart Gang!  \nFeel free to let it rip!\n", "image_url": "https://i.seadn.io/s/raw/files/18bea82408c4c778cfb7601a388fb2ad.png?w=500&auto=format", "banner_image_url": "https://i.seadn.io/s/primary-drops/0x88d186905c20aa7b3e2e3a3090f2a1074f8cc564/34316136:about:media:0e6e4737-88bd-4e3d-b0c8-90626a25f6d1.png?w=500&auto=format", "owner": "0x214ca916445b284e2b535330926b0175af47f309", "safelist_status": "not_requested", "category": "pfps", "is_disabled": false, "is_nsfw": false, "trait_offers_enabled": true, "collection_offers_enabled": true, "opensea_url": "https://opensea.io/collection/blockchain-fart-gang", "project_url": "https://www.blockchainfartgang.com/", "wiki_url": "", "discord_url": "", "telegram_url": "", "twitter_username": "FartBlastLabs", "instagram_username": "", "contracts": [{"address": "0x88d186905c20aa7b3e2e3a3090f2a1074f8cc564", "chain": "ethereum"}]}, {"collection": "fun2-1", "name": "fun2", "description": "", "image_url": "https://i.seadn.io/s/raw/files/c70db574ecb91a9d7dbdbe6a1eda1525.png?w=500&auto=format", "banner_image_url": "", "owner": "0x2c919de13094e80ef915bb03ae89970a88fdca41", "safelist_status": "not_requested", "category": "", "is_disabled": false, "is_nsfw": false, "trait_offers_enabled": false, "collection_offers_enabled": true, "opensea_url": "https://opensea.io/collection/fun2-1", "project_url": "", "wiki_url": "", "discord_url": "", "telegram_url": "", "twitter_username": "", "instagram_username": "", "contracts": [{"address": "0xc5c131568725ba759d4f72dd4ec05c9a1e994a55", "chain": "ethereum"}]}, {"collection": "fun-234", "name": "fun", "description": "", "image_url": "https://i.seadn.io/s/raw/files/9b4239683d549a4ba70a37c3c2a40bfb.png?w=500&auto=format", "banner_image_url": "", "owner": "0x3ece80e12aa51aa6e082004afaf3648a7b769e2e", "safelist_status": "not_requested", "category": "", "is_disabled": false, "is_nsfw": false, "trait_offers_enabled": false, "collection_offers_enabled": true, "opensea_url": "https://opensea.io/collection/fun-234", "project_url": "", "wiki_url": "", "discord_url": "", "telegram_url": "", "twitter_username": "", "instagram_username": "", "contracts": [{"address": "0x04a94969f4075fdd9b922d630689f6e78d0e53f3", "chain": "ethereum"}]}, {"collection": "resonance-labs", "name": "Resonance Labs", "description": "", "image_url": "https://i.seadn.io/s/raw/files/674c0b2594a2b43ebeba8bd51dc02669.jpg?w=500&auto=format", "banner_image_url": "https://i.seadn.io/s/primary-drops/0x20eba1ac07c022c14d7fe2be8ba7c298f83e62eb/34316062:about:media:931ddd3b-ed03-4b18-b07d-380cf1a759fc.jpeg?w=500&auto=format", "owner": "0x3ed9707718a0a41464c905aed5fbc5a067236c0e", "safelist_status": "not_requested", "category": "memberships", "is_disabled": false, "is_nsfw": false, "trait_offers_enabled": false, "collection_offers_enabled": true, "opensea_url": "https://opensea.io/collection/resonance-labs", "project_url": "https://resonancelabs.art/", "wiki_url": "", "discord_url": "https://discord.gg/YmzTmR2MsW", "telegram_url": "", "twitter_username": "resonance_lab", "instagram_username": "", "contracts": [{"address": "0x20eba1ac07c022c14d7fe2be8ba7c298f83e62eb", "chain": "ethereum"}]}, {"collection": "quazar-1", "name": "quazar", "description": "Beautiful and bright.  The brightest shining stars combined together creating the perfect view from above.   ", "image_url": "https://i.seadn.io/s/raw/files/471b2cd97d1d9081da5e6a14added149.jpg?w=500&auto=format", "banner_image_url": "", "owner": "0xed1af346bedbda157a35b253ab64fc6d1c435ed6", "safelist_status": "not_requested", "category": "", "is_disabled": false, "is_nsfw": false, "trait_offers_enabled": false, "collection_offers_enabled": true, "opensea_url": "https://opensea.io/collection/quazar-1", "project_url": "", "wiki_url": "", "discord_url": "", "telegram_url": "", "twitter_username": "", "instagram_username": "", "contracts": [{"address": "0x8a98ee9504ebb6e4519b1fac8a09627166cad089", "chain": "ethereum"}]}, {"collection": "collectibles-in-animation", "name": "Collectibles in Animation", "description": "Dandy Lemur is a collection of an unusual long-necked and very graceful cartoon\nAi digital art NFT's video and sound improved and retouched with design tools. ", "image_url": "https://i.seadn.io/s/raw/files/b72372be14372da0e857cfc4c2ba9afb.png?w=500&auto=format", "banner_image_url": "https://i.seadn.io/s/primary-drops/0xfd5b7e28a20c76f2023f11999c092c97983bea72/34316032:about:media:ef76c83f-a5e5-402a-a54c-21b7d8515cc4.png?w=500&auto=format", "owner": "0xb7f0c1251598f275abbeb32ca5c8068dbdb7d62e", "safelist_status": "not_requested", "category": "virtual-worlds", "is_disabled": false, "is_nsfw": false, "trait_offers_enabled": false, "collection_offers_enabled": true, "opensea_url": "https://opensea.io/collection/collectibles-in-animation", "project_url": "", "wiki_url": "", "discord_url": "", "telegram_url": "", "twitter_username": "aleromantillam1", "instagram_username": "", "contracts": [{"address": "0xfd5b7e28a20c76f2023f11999c092c97983bea72", "chain": "ethereum"}]}, {"collection": "song-a-day-on-networked-art", "name": "Song A Day On Networked Art", "description": "Song A Day's home on Mint/Networked Art.", "image_url": "https://i.seadn.io/s/raw/files/5ed2b93dc653c2161c9d90087c4a4dab.jpg?w=500&auto=format", "banner_image_url": "", "owner": "0x3d9456ad6463a77bd77123cb4836e463030bfab4", "safelist_status": "not_requested", "category": "", "is_disabled": false, "is_nsfw": false, "trait_offers_enabled": false, "collection_offers_enabled": true, "opensea_url": "https://opensea.io/collection/song-a-day-on-networked-art", "project_url": "", "wiki_url": "", "discord_url": "", "telegram_url": "", "twitter_username": "", "instagram_username": "", "contracts": [{"address": "0xfb2c594818d82ab1b77b6f3258136523de380a64", "chain": "ethereum"}]}, {"collection": "gods-of-sumer", "name": "Gods of Sumer", "description": "Gods of Sumer: CyberPantheon\n\nAncient Divinity Reforged in the Age of Neon.\nBefore time was measured in data streams, before cities pulsed with digital light, the gods of Sumer ruled over the cosmos. Their will shaped the heavens and the earth, their power dictated the fates of mortals. Now, in the age of cybernetic rebirth, these ancient deities rise again\u2014rewired, reengineered, and more powerful than ever.\nFrom Anu, the Supreme Cyber Ruler of the Digital Heavens, to Ereshkigal, the Neon Queen of the Underworld, each divine being has been resurrected in Neo-Uruk, their celestial forms rebuilt with quantum alloys and pulsating data cores. Wielding weapons forged from pure code and elemental energy, they walk the streets of a futuristic metaverse, where myth and fantasy collide.\nThis exclusive collection reimagines the most powerful gods, warriors, and rulers of Mesopotamian legend in a cyberpunk-fused digital realm, offering collectors a chance to own a fragment of divine power.", "image_url": "https://i.seadn.io/s/raw/files/ce42c117bbccbbb83e1f985532d06b33.jpg?w=500&auto=format", "banner_image_url": "https://i.seadn.io/s/primary-drops/0x4ee2fcbf9ad851adce8764377c348c8f43cfa59c/34315953:about:media:e5a42c0e-adbb-4df3-8035-03a0b7328741.jpeg?w=500&auto=format", "owner": "0xe9bfc6efa9164fa2b45adf77f896f79a44249008", "safelist_status": "not_requested", "category": "art", "is_disabled": false, "is_nsfw": false, "trait_offers_enabled": true, "collection_offers_enabled": true, "opensea_url": "https://opensea.io/collection/gods-of-sumer", "project_url": "", "wiki_url": "", "discord_url": "", "telegram_url": "https://t.me/+uDyiMuUcOPFhNzI8", "twitter_username": "crynftguy", "instagram_username": "", "contracts": [{"address": "0x4ee2fcbf9ad851adce8764377c348c8f43cfa59c", "chain": "ethereum"}]}, {"collection": "solid-nft-3", "name": "SOLID (NFT)", "description": "", "image_url": "https://i.seadn.io/s/raw/files/63f4f1b09c6062dd700e029a916b32ba.png?w=500&auto=format", "banner_image_url": "", "owner": "0x5180fb37b23cbd077723e72b5b6745e37931680d", "safelist_status": "not_requested", "category": "", "is_disabled": false, "is_nsfw": false, "trait_offers_enabled": false, "collection_offers_enabled": true, "opensea_url": "https://opensea.io/collection/solid-nft-3", "project_url": "", "wiki_url": "", "discord_url": "", "telegram_url": "", "twitter_username": "", "instagram_username": "", "contracts": [{"address": "0xf7ab06f26796a9f89ce0240e2fcc65d83fc107df", "chain": "ethereum"}]}, {"collection": "kia-21", "name": "kia", "description": "", "image_url": "", "banner_image_url": "", "owner": "0x1981bda8e86728ef726ba1eb16842a15256f9dcb", "safelist_status": "not_requested", "category": "", "is_disabled": false, "is_nsfw": false, "trait_offers_enabled": false, "collection_offers_enabled": true, "opensea_url": "https://opensea.io/collection/kia-21", "project_url": "", "wiki_url": "", "discord_url": "", "telegram_url": "", "twitter_username": "", "instagram_username": "", "contracts": [{"address": "0x9d84e75212ee8b08fd14712d343744afe1f57e6d", "chain": "ethereum"}]}, {"collection": "bylittleelise", "name": "bylittleelise", "description": "", "image_url": "https://i.seadn.io/s/raw/files/521d0cf88a94510cffc86f9f4e406970.png?w=500&auto=format", "banner_image_url": "https://i.seadn.io/s/primary-drops/0x4497bfb845522fcb3e90fd7e1e4c037f525e1295/34315823:about:media:d6864ec9-d4b3-4aef-9a7a-05626227ef36.png?w=500&auto=format", "owner": "0x1bcd94554cf25f4004e900463f0921349746d054", "safelist_status": "not_requested", "category": "art", "is_disabled": false, "is_nsfw": false, "trait_offers_enabled": false, "collection_offers_enabled": true, "opensea_url": "https://opensea.io/collection/bylittleelise", "project_url": "https://linktr.ee/bylittleelise", "wiki_url": "", "discord_url": "", "telegram_url": "", "twitter_username": "bylittleelise", "instagram_username": "", "contracts": [{"address": "0x4497bfb845522fcb3e90fd7e1e4c037f525e1295", "chain": "ethereum"}]}, {"collection": "flat-bottom-egg-and-chili", "name": "Flat bottom egg and chili", "description": "Flatbottom Egg and Chili", "image_url": "", "banner_image_url": "", "owner": "0x0381b35998bb6e6396a1721b10c8d1d62439251b", "safelist_status": "not_requested", "category": "art", "is_disabled": false, "is_nsfw": false, "trait_offers_enabled": false, "collection_offers_enabled": false, "opensea_url": "https://opensea.io/collection/flat-bottom-egg-and-chili", "project_url": "", "wiki_url": "", "discord_url": "", "telegram_url": "", "twitter_username": "", "instagram_username": "", "contracts": [{"address": "0x9bf558654b40fc93bca59a1cd04f98946ddeaa62", "chain": "ethereum"}]}, {"collection": "flysk8", "name": "FLYSK8", "description": "FLYSK8 is the only and first crypto art project in the world made by a skateboarder! Which brings together the world of art, design, and pop and street culture through the creation of collectible NFT art paintings. FLYSK8 is designed to reflect the character and diversity of the skater, symbolizing persistence, transformation and growth. The FLYSK8 collection is a collaboration with famous personalities in the world of skateboarding, extreme sports, artists and brands that have had a significant impact on modern culture and generations. Attention to detail and craftsmanship ensure that each art painting is a unique and valuable addition to any collection.", "image_url": "https://i.seadn.io/s/raw/files/532e7aa6b8979d7f6148dad1fcce0cf1.png?w=500&auto=format", "banner_image_url": "https://i.seadn.io/s/primary-drops/0x3cecb062031a42ee452ff7cd7d6eaa8837ceaf34/34315652:about:media:969531d8-f072-4b3c-a432-6e2ef4130de2.png?w=500&auto=format", "owner": "0x6a58e23b6f2426ddb37172658d6d47e595a28541", "safelist_status": "not_requested", "category": "art", "is_disabled": false, "is_nsfw": false, "trait_offers_enabled": false, "collection_offers_enabled": true, "opensea_url": "https://opensea.io/collection/flysk8", "project_url": "", "wiki_url": "", "discord_url": "", "telegram_url": "", "twitter_username": "", "instagram_username": "", "contracts": [{"address": "0x3cecb062031a42ee452ff7cd7d6eaa8837ceaf34", "chain": "ethereum"}]}, {"collection": "surrealist-elephants", "name": "Surrealist elephants", "description": "Collection of surreal works of a dreamlike world where nature and time converge in a desert landscape full of symbolism. Elephants, exotic orchids, diverse characters, mystical felines and clocks that seem to defy reality, evoking a connection between imagination and consciousness. Every detail of these oil paintings captures enigmatic stories, inviting the observer to lose themselves in their depth and mystery.", "image_url": "https://i.seadn.io/s/raw/files/8387b9e4118c3b3a3048952d8156de20.jpg?w=500&auto=format", "banner_image_url": "", "owner": "0xa4547df98a9ed35ff0fb47c5fd4612b8f2798c95", "safelist_status": "not_requested", "category": "art", "is_disabled": false, "is_nsfw": false, "trait_offers_enabled": false, "collection_offers_enabled": true, "opensea_url": "https://opensea.io/collection/surrealist-elephants", "project_url": "", "wiki_url": "", "discord_url": "", "telegram_url": "", "twitter_username": "", "instagram_username": "", "contracts": [{"address": "0x118e0ae096a353ed383a79831c4e0a26c390cebf", "chain": "ethereum"}]}, {"collection": "poptrashartist", "name": "PopTrashArtist", "description": "", "image_url": "https://i.seadn.io/s/raw/files/dbc807e804605ede6b6d5e3f5e9d0bca.png?w=500&auto=format", "banner_image_url": "", "owner": "0x16cb6c5b30dbc1e670932bb887fb59dda6352912", "safelist_status": "not_requested", "category": "", "is_disabled": false, "is_nsfw": false, "trait_offers_enabled": false, "collection_offers_enabled": true, "opensea_url": "https://opensea.io/collection/poptrashartist", "project_url": "", "wiki_url": "", "discord_url": "", "telegram_url": "", "twitter_username": "", "instagram_username": "", "contracts": [{"address": "0x81ecfda163d354d5e9d222c0579eba4e6c6312f0", "chain": "ethereum"}]}, {"collection": "videos-for-friends-and-family", "name": "Videos for friends and family", "description": "", "image_url": "https://i.seadn.io/s/raw/files/217e2aa3dbe20550656ceb3129ccaeac.jpg?w=500&auto=format", "banner_image_url": "", "owner": "0x0eb00a20ddb5ee45b86b06e5426d18ce46789867", "safelist_status": "not_requested", "category": "", "is_disabled": false, "is_nsfw": false, "trait_offers_enabled": false, "collection_offers_enabled": true, "opensea_url": "https://opensea.io/collection/videos-for-friends-and-family", "project_url": "", "wiki_url": "", "discord_url": "", "telegram_url": "", "twitter_username": "", "instagram_username": "", "contracts": [{"address": "0xba7737635ee77f5c260cdf7686db120a2fb6a800", "chain": "ethereum"}]}, {"collection": "adys-nature-collection", "name": "Adys Nature Collection", "description": "", "image_url": "https://i.seadn.io/s/raw/files/c4f27c42e16315a78f96df1cc69ae3a9.png?w=500&auto=format", "banner_image_url": "", "owner": "0x8f796f94ed814904072101c4db485c24c09d8bcc", "safelist_status": "not_requested", "category": "", "is_disabled": false, "is_nsfw": false, "trait_offers_enabled": false, "collection_offers_enabled": true, "opensea_url": "https://opensea.io/collection/adys-nature-collection", "project_url": "", "wiki_url": "", "discord_url": "", "telegram_url": "", "twitter_username": "", "instagram_username": "", "contracts": [{"address": "0x46c92cae8350396490fb23cd2989f118c063446e", "chain": "ethereum"}]}, {"collection": "heyabe", "name": "HEYABE", "description": "", "image_url": "https://i.seadn.io/s/raw/files/9b3e07b725c5d11d347d1ae3bec2c83a.webp?w=500&auto=format", "banner_image_url": "", "owner": "0x181891e858345de95fd43214c86c5748e451d881", "safelist_status": "not_requested", "category": "", "is_disabled": false, "is_nsfw": false, "trait_offers_enabled": false, "collection_offers_enabled": true, "opensea_url": "https://opensea.io/collection/heyabe", "project_url": "", "wiki_url": "", "discord_url": "", "telegram_url": "", "twitter_username": "", "instagram_username": "", "contracts": [{"address": "0xc91611ffc1c3014471184a955cc4612e586af8e6", "chain": "ethereum"}]}, {"collection": "my-first-eth-collection", "name": "My First ETH Collection", "description": "", "image_url": "https://i.seadn.io/s/raw/files/921401400194bb1162d1810e858eff3e.png?w=500&auto=format", "banner_image_url": "", "owner": "0xb762165f28888cac07278cdee3fa8cd0f061b276", "safelist_status": "not_requested", "category": "", "is_disabled": false, "is_nsfw": false, "trait_offers_enabled": false, "collection_offers_enabled": true, "opensea_url": "https://opensea.io/collection/my-first-eth-collection", "project_url": "", "wiki_url": "", "discord_url": "", "telegram_url": "", "twitter_username": "", "instagram_username": "", "contracts": [{"address": "0xfbd22c57f67c0728ffdf4a4fdf61ec5fe0a178d5", "chain": "ethereum"}]}, {"collection": "raven-warrior-gif", "name": "Raven Warrior Gif", "description": "", "image_url": "https://i.seadn.io/s/raw/files/9079660dc4308e1a02bcb43107f296bb.gif?w=500&auto=format", "banner_image_url": "", "owner": "0xf8a6ea1cd49bf0d6f7b6ac0a7cf205a865e4f060", "safelist_status": "not_requested", "category": "", "is_disabled": false, "is_nsfw": false, "trait_offers_enabled": false, "collection_offers_enabled": true, "opensea_url": "https://opensea.io/collection/raven-warrior-gif", "project_url": "", "wiki_url": "", "discord_url": "", "telegram_url": "", "twitter_username": "", "instagram_username": "", "contracts": [{"address": "0xa6c83c26fbff91a9ab793a81c0e8256c8b5758fc", "chain": "ethereum"}]}, {"collection": "catibara", "name": "Catibara", "description": "CATIBARA", "image_url": "https://i.seadn.io/s/raw/files/98cfb65837dfc6835573b0f78293fd97.jpg?w=500&auto=format", "banner_image_url": "", "owner": "0x3e79fbf7f1b1814800cb9adbca9fa6c929077d6c", "safelist_status": "not_requested", "category": "", "is_disabled": false, "is_nsfw": false, "trait_offers_enabled": false, "collection_offers_enabled": true, "opensea_url": "https://opensea.io/collection/catibara", "project_url": "", "wiki_url": "", "discord_url": "", "telegram_url": "", "twitter_username": "", "instagram_username": "", "contracts": [{"address": "0x6dfccb2498e39e9dfa548a60482dc125a14f61aa", "chain": "ethereum"}]}, {"collection": "ms-cherry", "name": "Ms. Cherry", "description": "", "image_url": "https://i.seadn.io/s/raw/files/84bb9f4d4ed0d35377ccc549f9c63437.jpg?w=500&auto=format", "banner_image_url": "", "owner": "0x1b9a99344595e929e2a95c09346044b9c98ec40c", "safelist_status": "not_requested", "category": "", "is_disabled": false, "is_nsfw": false, "trait_offers_enabled": false, "collection_offers_enabled": true, "opensea_url": "https://opensea.io/collection/ms-cherry", "project_url": "", "wiki_url": "", "discord_url": "", "telegram_url": "", "twitter_username": "", "instagram_username": "", "contracts": [{"address": "0xba89ff58fcfee8ef6ce0f88eed54ecdfcbd7db1c", "chain": "ethereum"}]}, {"collection": "npinm-collection", "name": "NPinM Collection", "description": "", "image_url": "https://i.seadn.io/s/raw/files/9f2ad00302585ed8ab7cae2cfdea8705.gif?w=500&auto=format", "banner_image_url": "", "owner": "0xee0ebd0b4e4bb96d107d2bf8e13159446e65e2b4", "safelist_status": "not_requested", "category": "", "is_disabled": false, "is_nsfw": false, "trait_offers_enabled": false, "collection_offers_enabled": true, "opensea_url": "https://opensea.io/collection/npinm-collection", "project_url": "", "wiki_url": "", "discord_url": "", "telegram_url": "", "twitter_username": "", "instagram_username": "", "contracts": [{"address": "0x8e50b27e314585cb371e6b779769653dfc572885", "chain": "ethereum"}]}, {"collection": "shrine-maiden-fortune-teller", "name": "Shrine maiden fortune teller", "description": "", "image_url": "https://i.seadn.io/s/raw/files/72ac5d7d2731cbda1032d31d21c2c021.png?w=500&auto=format", "banner_image_url": "", "owner": "0xc11d4301bfb6c76b229f3ab331194110836e77ba", "safelist_status": "not_requested", "category": "", "is_disabled": false, "is_nsfw": false, "trait_offers_enabled": false, "collection_offers_enabled": true, "opensea_url": "https://opensea.io/collection/shrine-maiden-fortune-teller", "project_url": "", "wiki_url": "", "discord_url": "", "telegram_url": "", "twitter_username": "", "instagram_username": "", "contracts": [{"address": "0xb69c0ab9a4b263d424ed05f0a8a878e1d8772b72", "chain": "ethereum"}]}, {"collection": "beach-scenes-4", "name": "Beach Scenes", "description": "", "image_url": "https://i.seadn.io/s/raw/files/2ec264d12c081ae87a97c93ab06a2f77.webp?w=500&auto=format", "banner_image_url": "", "owner": "0xc6ea94cd696650f216d3072a819fc825fc58ae94", "safelist_status": "not_requested", "category": "art", "is_disabled": false, "is_nsfw": false, "trait_offers_enabled": false, "collection_offers_enabled": true, "opensea_url": "https://opensea.io/collection/beach-scenes-4", "project_url": "", "wiki_url": "", "discord_url": "", "telegram_url": "", "twitter_username": "", "instagram_username": "", "contracts": [{"address": "0xf9f7de9db8993758c7098ce5f4714272d8760deb", "chain": "ethereum"}]}, {"collection": "masks-of-the-unknown-1", "name": "Masks of the unknown", "description": "", "image_url": "", "banner_image_url": "", "owner": "0x5a82d04b3a4d16dd6b468f7da480ff474a3f63c1", "safelist_status": "not_requested", "category": "", "is_disabled": false, "is_nsfw": false, "trait_offers_enabled": false, "collection_offers_enabled": false, "opensea_url": "https://opensea.io/collection/masks-of-the-unknown-1", "project_url": "", "wiki_url": "", "discord_url": "", "telegram_url": "", "twitter_username": "", "instagram_username": "", "contracts": [{"address": "0x5fb22253c177ee499fd59195381910dac596cc0f", "chain": "ethereum"}]}, {"collection": "still-life-arsenal-2", "name": "Still life arsenal", "description": "", "image_url": "", "banner_image_url": "", "owner": "0x26f912a1ec4721fa4372edb2379d0938a2407d8e", "safelist_status": "not_requested", "category": "", "is_disabled": false, "is_nsfw": false, "trait_offers_enabled": false, "collection_offers_enabled": false, "opensea_url": "https://opensea.io/collection/still-life-arsenal-2", "project_url": "", "wiki_url": "", "discord_url": "", "telegram_url": "", "twitter_username": "", "instagram_username": "", "contracts": [{"address": "0x1b7a55e8eb744179dbe8ab834422170884809a80", "chain": "ethereum"}]}, {"collection": "pycc", "name": "PunkyChaps Club", "description": "", "image_url": "https://i.seadn.io/s/raw/files/021ebf709689f07344cac83c42a4fbe1.jpg?w=500&auto=format", "banner_image_url": "https://i.seadn.io/s/primary-drops/0xaf6cd3c6a78de9279e834874eaa6e4727f3e0851/34314828:about:media:01a6fda6-1a1c-4507-a7bd-61d24aea8cd6.png?w=500&auto=format", "owner": "0x6cc94e3951b3b40c0f0cf868368b021117a77d32", "safelist_status": "not_requested", "category": "", "is_disabled": false, "is_nsfw": false, "trait_offers_enabled": false, "collection_offers_enabled": true, "opensea_url": "https://opensea.io/collection/pycc", "project_url": "", "wiki_url": "", "discord_url": "", "telegram_url": "", "twitter_username": "", "instagram_username": "", "contracts": [{"address": "0xaf6cd3c6a78de9279e834874eaa6e4727f3e0851", "chain": "ethereum"}]}, {"collection": "chaosera", "name": "Chaos Era", "description": "Where the world of web3 and chaos collide", "image_url": "https://i.seadn.io/s/raw/files/3f5e14d71967b2820f41115b4b9bec1f.jpg?w=500&auto=format", "banner_image_url": "https://i.seadn.io/s/primary-drops/0x9d85b0d04b60f37ed192bfe0682a4f33175c9cc8/34314806:about:media:bc03eaeb-6d93-467e-9594-e09fc2d72604.jpeg?w=500&auto=format", "owner": "0x339ea14d82373cdbd329ad32a1f192d3c5c1efc4", "safelist_status": "approved", "category": "art", "is_disabled": false, "is_nsfw": false, "trait_offers_enabled": false, "collection_offers_enabled": true, "opensea_url": "https://opensea.io/collection/chaosera", "project_url": "", "wiki_url": "", "discord_url": "", "telegram_url": "", "twitter_username": "", "instagram_username": "", "contracts": [{"address": "0x9d85b0d04b60f37ed192bfe0682a4f33175c9cc8", "chain": "ethereum"}]}, {"collection": "still-life-arsenal-1", "name": "Still life arsenal", "description": "", "image_url": "https://i.seadn.io/s/raw/files/01cf81e7e124a9a3e932fcfa7df401a5.png?w=500&auto=format", "banner_image_url": "", "owner": "0x26f912a1ec4721fa4372edb2379d0938a2407d8e", "safelist_status": "not_requested", "category": "", "is_disabled": false, "is_nsfw": false, "trait_offers_enabled": false, "collection_offers_enabled": true, "opensea_url": "https://opensea.io/collection/still-life-arsenal-1", "project_url": "", "wiki_url": "", "discord_url": "", "telegram_url": "", "twitter_username": "", "instagram_username": "", "contracts": [{"address": "0xb4ac2a2c01bd12aa720dd30e664dd9b0e17e8034", "chain": "ethereum"}]}, {"collection": "mystic-realms-jessdigiart", "name": "Mystic Realms", "description": "Immerse yourself in a world of ethereal beauty and boundless imagination. Each design captures the magic of surreal landscapes, from moonlit valleys to vibrant floral horizons. Let these enchanting sceneries inspire your dreams and awaken a sense of wonder within you.", "image_url": "https://i.seadn.io/s/raw/files/c7d857cc456ff0933129b92672499c4c.jpg?w=500&auto=format", "banner_image_url": "", "owner": "0xa56ca7fa0a4e8ed4e41f77f431ab8adfcb991824", "safelist_status": "not_requested", "category": "art", "is_disabled": false, "is_nsfw": false, "trait_offers_enabled": false, "collection_offers_enabled": true, "opensea_url": "https://opensea.io/collection/mystic-realms-jessdigiart", "project_url": "", "wiki_url": "", "discord_url": "", "telegram_url": "", "twitter_username": "", "instagram_username": "", "contracts": [{"address": "0x79cf0080c6deaecb2891a88754058f7d1fddc21c", "chain": "ethereum"}]}, {"collection": "still-life-arsenal", "name": "Still life arsenal", "description": "", "image_url": "https://i.seadn.io/s/raw/files/5f9ecadf18f02e3e54dccdbefb590f2d.png?w=500&auto=format", "banner_image_url": "", "owner": "0x26f912a1ec4721fa4372edb2379d0938a2407d8e", "safelist_status": "not_requested", "category": "art", "is_disabled": false, "is_nsfw": false, "trait_offers_enabled": false, "collection_offers_enabled": true, "opensea_url": "https://opensea.io/collection/still-life-arsenal", "project_url": "", "wiki_url": "", "discord_url": "", "telegram_url": "", "twitter_username": "", "instagram_username": "", "contracts": [{"address": "0xb47717cc6f234603eaed9be09d4cf11a6b7da3c7", "chain": "ethereum"}]}, {"collection": "turtle-world-3", "name": "Turtle World", "description": "", "image_url": "https://i.seadn.io/s/raw/files/f3238558dcfeb71942705fbe9eb6566a.png?w=500&auto=format", "banner_image_url": "", "owner": "0x5c23cb7827afd4c213d4cc149fe49e6d4c56bb6b", "safelist_status": "not_requested", "category": "", "is_disabled": false, "is_nsfw": false, "trait_offers_enabled": false, "collection_offers_enabled": true, "opensea_url": "https://opensea.io/collection/turtle-world-3", "project_url": "", "wiki_url": "", "discord_url": "", "telegram_url": "", "twitter_username": "", "instagram_username": "", "contracts": [{"address": "0xf50e60f43e973fe6149d90d867a9a4e5d4271ffa", "chain": "ethereum"}]}, {"collection": "artificial-financial-intelligence", "name": "Artificial Financial Intelligence", "description": "", "image_url": "https://i.seadn.io/s/raw/files/b9d8a86070ec8c132036cd115f142b49.jpg?w=500&auto=format", "banner_image_url": "", "owner": "0x0a7381517c8c9ff85c06202c328b2b65ffb9cc17", "safelist_status": "not_requested", "category": "", "is_disabled": false, "is_nsfw": false, "trait_offers_enabled": false, "collection_offers_enabled": true, "opensea_url": "https://opensea.io/collection/artificial-financial-intelligence", "project_url": "", "wiki_url": "", "discord_url": "", "telegram_url": "", "twitter_username": "", "instagram_username": "", "contracts": [{"address": "0xc1290b87ab65b1084f29ffc72da8c456c7d46c0c", "chain": "ethereum"}]}, {"collection": "extremelyrare-1", "name": "extremelyrare", "description": "this non fungible token is an immutable fraction of something extremely rare", "image_url": "https://i.seadn.io/s/raw/files/48825d9e7999e9e0a761fca750cb7179.jpg?w=500&auto=format", "banner_image_url": "", "owner": "0xd45db98a557c4a44b34c3ec8887453e502f75105", "safelist_status": "not_requested", "category": "", "is_disabled": false, "is_nsfw": false, "trait_offers_enabled": false, "collection_offers_enabled": true, "opensea_url": "https://opensea.io/collection/extremelyrare-1", "project_url": "", "wiki_url": "", "discord_url": "", "telegram_url": "", "twitter_username": "", "instagram_username": "", "contracts": [{"address": "0xb10176173579b47b8da24c54201c5bfe3fe8579b", "chain": "ethereum"}]}, {"collection": "ethereal-beauties-2", "name": "Ethereal Beauties", "description": "Ethereal Beauties is a collection of exquisite NFT paintings capturing the beauty, grace, and mystery of young women. Each artwork is a masterful portrayal of feminine elegance, blending realism with a touch of dreamlike charm.\n\nEvery piece in this collection tells a story\u2014of fleeting moments, deep emotions, and the timeless allure of youth. The delicate interplay of light, color, and expression brings these muses to life, making each NFT a unique and mesmerizing digital masterpiece.\n\nEthereal Beauties is more than just a celebration of beauty; it\u2019s an artistic tribute to the essence of femininity, forever preserved on the blockchain.", "image_url": "https://i.seadn.io/s/raw/files/66a7b7ff3593be7f081b2f502b3f57ee.png?w=500&auto=format", "banner_image_url": "", "owner": "0xc364859ed681cf5f0acb72daebd413e7eb529c44", "safelist_status": "not_requested", "category": "art", "is_disabled": false, "is_nsfw": false, "trait_offers_enabled": false, "collection_offers_enabled": true, "opensea_url": "https://opensea.io/collection/ethereal-beauties-2", "project_url": "", "wiki_url": "", "discord_url": "", "telegram_url": "", "twitter_username": "", "instagram_username": "", "contracts": [{"address": "0xf52bd66af11ff4f70a2f8b7ec0c25457c9897f95", "chain": "ethereum"}]}, {"collection": "apu-apustaja-year-1-raider-nft-edits", "name": "Apu Apustaja year 1 raider NFT edits", "description": "Personalized NFT edits for Apu frens that joined any time in year 1 ", "image_url": "https://i.seadn.io/s/raw/files/7f80591c29ea8256d29c183a27eb45f0.jpg?w=500&auto=format", "banner_image_url": "", "owner": "0x47e9875ebd90aa12fa76d2289ad270cf1470bb22", "safelist_status": "not_requested", "category": "", "is_disabled": false, "is_nsfw": false, "trait_offers_enabled": false, "collection_offers_enabled": true, "opensea_url": "https://opensea.io/collection/apu-apustaja-year-1-raider-nft-edits", "project_url": "", "wiki_url": "", "discord_url": "", "telegram_url": "", "twitter_username": "", "instagram_username": "", "contracts": [{"address": "0x4be122186acaee89eb1bb184476bee770a0d37fb", "chain": "ethereum"}]}, {"collection": "outrunyouth-1-1s", "name": "Outrunyouth 1/1s", "description": "", "image_url": "https://i.seadn.io/s/raw/files/dee5efee66ae4165c9321aaf5275fff9.jpg?w=500&auto=format", "banner_image_url": "", "owner": "0x10ee6468f5d970cfb3cdb4e0866e9816b4e09e3c", "safelist_status": "not_requested", "category": "", "is_disabled": false, "is_nsfw": false, "trait_offers_enabled": false, "collection_offers_enabled": true, "opensea_url": "https://opensea.io/collection/outrunyouth-1-1s", "project_url": "", "wiki_url": "", "discord_url": "", "telegram_url": "", "twitter_username": "", "instagram_username": "", "contracts": [{"address": "0x0b6ce877ac4de031f02d825a44287c1b1befd88b", "chain": "ethereum"}]}, {"collection": "the-unknows-s", "name": "The Unknows's", "description": "", "image_url": "https://i.seadn.io/s/raw/files/e550d342625aad6b0150acf868acaea6.jpg?w=500&auto=format", "banner_image_url": "", "owner": "0xd0f172a6a23b791a55144354d7647feba771109d", "safelist_status": "not_requested", "category": "", "is_disabled": false, "is_nsfw": false, "trait_offers_enabled": false, "collection_offers_enabled": true, "opensea_url": "https://opensea.io/collection/the-unknows-s", "project_url": "", "wiki_url": "", "discord_url": "", "telegram_url": "", "twitter_username": "", "instagram_username": "", "contracts": [{"address": "0x7e6c83bb41d75b15896ab731405201667ba0ec80", "chain": "ethereum"}]}, {"collection": "devils-fruit", "name": "Devil's Fruit", "description": "", "image_url": "https://i.seadn.io/s/raw/files/7517b45ffd7d79e3db98f755d377864f.jpg?w=500&auto=format", "banner_image_url": "", "owner": "0x5fbd95491d21dbd568b0da8889667f0a61ac6232", "safelist_status": "not_requested", "category": "art", "is_disabled": false, "is_nsfw": false, "trait_offers_enabled": false, "collection_offers_enabled": true, "opensea_url": "https://opensea.io/collection/devils-fruit", "project_url": "", "wiki_url": "", "discord_url": "", "telegram_url": "", "twitter_username": "", "instagram_username": "", "contracts": [{"address": "0x729ef475315b432be31064823daa69ea175c34c3", "chain": "ethereum"}]}, {"collection": "quote-35", "name": "Quote", "description": "", "image_url": "https://i.seadn.io/s/raw/files/d66b16e16c282ae5921be6497efe3bd2.webp?w=500&auto=format", "banner_image_url": "", "owner": "0x094e11f092228bc19466db0b1b22dd3e90171856", "safelist_status": "not_requested", "category": "art", "is_disabled": false, "is_nsfw": false, "trait_offers_enabled": false, "collection_offers_enabled": true, "opensea_url": "https://opensea.io/collection/quote-35", "project_url": "", "wiki_url": "", "discord_url": "", "telegram_url": "", "twitter_username": "", "instagram_username": "", "contracts": [{"address": "0x7d04719262716bb969fce348c5ac1c277b239e33", "chain": "ethereum"}]}, {"collection": "lovelyphotozz", "name": "LovelyPhotozz", "description": "", "image_url": "https://i.seadn.io/s/raw/files/712cd32de78dc8859a14639ed90aff26.jpg?w=500&auto=format", "banner_image_url": "", "owner": "0x22abf1ef60de6b1599304b7c0e153a0dc4ee2bdf", "safelist_status": "not_requested", "category": "photography", "is_disabled": false, "is_nsfw": false, "trait_offers_enabled": false, "collection_offers_enabled": true, "opensea_url": "https://opensea.io/collection/lovelyphotozz", "project_url": "", "wiki_url": "", "discord_url": "", "telegram_url": "", "twitter_username": "", "instagram_username": "", "contracts": [{"address": "0xd1952128b3ff774b2e9a8912c21c6360f3bac5f1", "chain": "ethereum"}]}, {"collection": "bored-nemirod", "name": "Bored Nemirod", "description": "", "image_url": "https://i.seadn.io/s/raw/files/52268aea484fe06a27c3a9848e119aab.jpg?w=500&auto=format", "banner_image_url": "", "owner": "0xaaa1578ebb9fc2c34d8ebe07166eaa3f7f83b688", "safelist_status": "not_requested", "category": "", "is_disabled": false, "is_nsfw": false, "trait_offers_enabled": false, "collection_offers_enabled": true, "opensea_url": "https://opensea.io/collection/bored-nemirod", "project_url": "", "wiki_url": "", "discord_url": "", "telegram_url": "", "twitter_username": "", "instagram_username": "", "contracts": [{"address": "0x6d2723760aabc3ee0b466a12cae1acb404e0928b", "chain": "ethereum"}]}, {"collection": "reimagined-masterpieces-1", "name": "Reimagined Masterpieces", "description": "Reimagined Masterpieces is a collection of unique NFTs that breathe new life into classic art through a modern lens. Each piece transforms renowned masterpieces, infusing them with fresh perspectives, contemporary styles, and unexpected twists.\n\nThis collection is a tribute to artistic evolution\u2014where the past meets the future, and tradition merges with innovation. Every artwork is a bold reinterpretation, capturing the essence of the original while reshaping it into something entirely new and captivating.\n\nReimagined Masterpieces invites collectors to explore familiar beauty in a fresh way, owning digital tributes to timeless art, reimagined for the blockchain era.", "image_url": "https://i.seadn.io/s/raw/files/bb3e5656f2e799be0d959db6e4d14c76.png?w=500&auto=format", "banner_image_url": "", "owner": "0xc364859ed681cf5f0acb72daebd413e7eb529c44", "safelist_status": "not_requested", "category": "art", "is_disabled": false, "is_nsfw": false, "trait_offers_enabled": false, "collection_offers_enabled": true, "opensea_url": "https://opensea.io/collection/reimagined-masterpieces-1", "project_url": "", "wiki_url": "", "discord_url": "", "telegram_url": "", "twitter_username": "", "instagram_username": "", "contracts": [{"address": "0xbdbca22ff676db7b26f6de022dd4507b70a9a5c0", "chain": "ethereum"}]}, {"collection": "new-age-17", "name": "New Age", "description": "", "image_url": "https://i.seadn.io/s/raw/files/9d54a2c59b080fc5a0fd1a46704bd426.jpg?w=500&auto=format", "banner_image_url": "", "owner": "0xe778bbad8d5abe7ac46f32299e35ae09ea278b5a", "safelist_status": "not_requested", "category": "", "is_disabled": false, "is_nsfw": false, "trait_offers_enabled": false, "collection_offers_enabled": true, "opensea_url": "https://opensea.io/collection/new-age-17", "project_url": "", "wiki_url": "", "discord_url": "", "telegram_url": "", "twitter_username": "", "instagram_username": "", "contracts": [{"address": "0x261008331b50c9d74700dd00bb2a0907019246b9", "chain": "ethereum"}]}, {"collection": "untitled-discount-mint", "name": "UNTITLED DISCOUNT MINT", "description": "Grab a discount", "image_url": "https://i.seadn.io/s/raw/files/c8e83382c320c71e1fdbba6db2eb94a1.png?w=500&auto=format", "banner_image_url": "https://i.seadn.io/s/primary-drops/0x129d7697c280dd6598f74bab6610349fd7d6126c/34313854:about:media:edb99bf4-60d2-41b1-92cf-f1d836e00345.png?w=500&auto=format", "owner": "0x4033a25afa12cc32ba15dea01f879be4c988411a", "safelist_status": "not_requested", "category": "", "is_disabled": false, "is_nsfw": false, "trait_offers_enabled": false, "collection_offers_enabled": true, "opensea_url": "https://opensea.io/collection/untitled-discount-mint", "project_url": "", "wiki_url": "", "discord_url": "", "telegram_url": "", "twitter_username": "captainVickk", "instagram_username": "", "contracts": [{"address": "0x129d7697c280dd6598f74bab6610349fd7d6126c", "chain": "ethereum"}]}, {"collection": "web-3-innovation-lab-legacy-nfts", "name": "Web 3 Innovation Lab Legacy NFTs", "description": "", "image_url": "https://i.seadn.io/s/raw/files/2a8979d79ecd463602916458ce955930.png?w=500&auto=format", "banner_image_url": "", "owner": "0x66dcc49c47ebc505a4b560fd14dc143f0098407f", "safelist_status": "not_requested", "category": "", "is_disabled": false, "is_nsfw": false, "trait_offers_enabled": false, "collection_offers_enabled": true, "opensea_url": "https://opensea.io/collection/web-3-innovation-lab-legacy-nfts", "project_url": "", "wiki_url": "", "discord_url": "", "telegram_url": "", "twitter_username": "", "instagram_username": "", "contracts": [{"address": "0x007392c33cce375634d264a42cdcb21fbfbe47aa", "chain": "ethereum"}]}, {"collection": "nbs-1-1", "name": "Black Out", "description": "", "image_url": "https://i.seadn.io/s/raw/files/6bdb2253a7de4ad5cc52b1684cbb27b0.jpg?w=500&auto=format", "banner_image_url": "", "owner": "0x9cf0c7361c60e3ba16101c0462740dd828387209", "safelist_status": "not_requested", "category": "", "is_disabled": false, "is_nsfw": false, "trait_offers_enabled": false, "collection_offers_enabled": true, "opensea_url": "https://opensea.io/collection/nbs-1-1", "project_url": "", "wiki_url": "", "discord_url": "", "telegram_url": "", "twitter_username": "", "instagram_username": "", "contracts": [{"address": "0x6487bcdf89787c4816c584752603aac1e9fa89b1", "chain": "ethereum"}]}, {"collection": "corgidogz", "name": "CorgiDogz", "description": "\ud83d\udc36 CorgiDogz NFT Collection is a hand-drawn, limited-edition series of adorable corgi-inspired digital collectibles, designed to bring fun, utility, and community to the blockchain! Each CorgiDog is uniquely illustrated by talented artists, making every piece a true work of art. From playful expressions to legendary outfits, no two CorgiDogz are the same!\n\nhttps://opensea.io/collection/corgidogz\n\n\ud83c\udfa8 Collection Features:\n\u2705 100% Hand-Drawn Artwork \u2013 No auto-generations, just pure creativity!\n\u2705 Rare & Unique Traits \u2013 From astronaut suits to royal crowns, every CorgiDogz NFT tells a story!\n\u2705 Metaverse & Gaming Utility \u2013 Use your NFT for staking rewards, in-game perks, and more!\n\u2705 Breeding & Evolution \u2013 Combine CorgiDogz to create ultra-rare pups with enhanced traits!\n\nJoin the CorgiDogz Pack and own a one-of-a-kind, hand-crafted masterpiece that\u2019s not only cute but also crypto-powered! \ud83d\ude80", "image_url": "https://i.seadn.io/s/raw/files/9512ce15f5b5ba13f43052969e4d39a9.jpg?w=500&auto=format", "banner_image_url": "https://i.seadn.io/s/primary-drops/0x1651b56fbb12401a71d6c81a2ba203d2899c30f8/34313819:about:media:02afa700-dc83-4a29-a1f0-2acaece13290.jpeg?w=500&auto=format", "owner": "0x1f778b4bc6b3f2e06d481f3525b7d261df0f71df", "safelist_status": "not_requested", "category": "art", "is_disabled": false, "is_nsfw": false, "trait_offers_enabled": false, "collection_offers_enabled": true, "opensea_url": "https://opensea.io/collection/corgidogz", "project_url": "https://opensea.io/collection/corgidogz", "wiki_url": "", "discord_url": "", "telegram_url": "", "twitter_username": "", "instagram_username": "", "contracts": [{"address": "0x1651b56fbb12401a71d6c81a2ba203d2899c30f8", "chain": "ethereum"}]}, {"collection": "goblin-hood-3-fizzlewart", "name": "Goblin Hood 3 (Fizzlewart)", "description": "* This Goblin is Fizzlewart!  He is the 3rd NFT in the Goblin Hood Series, by artists at BitSwagger.org !\n* This Goblin Mp4 was beautifully designed by another artist with BitSwagger!  There are more to come each with a unique animation to add a little spark to the image; and the imagination!\n* A blend of fantasy art, digital layering,  & light animations; each goblin in this series will surely shine among your other collections, they are mesmerizing & beautiful images!  Thanks for all the support!\n* Goblin Hood is a concept for a name for part of our merchandising plans; for the BitSwagger digital art studio!  \n* More available at www.bitswagger.org!  These versions on Ethereum will be more rare, get yours while they last! \n* www.BitSwagger.org", "image_url": "https://i.seadn.io/s/raw/files/14dd109188a9dc7abb976bab14a491ca.gif?w=500&auto=format", "banner_image_url": "", "owner": "0x122f9b8d96e963aab0d9a109a2c0b4c5f4d05668", "safelist_status": "not_requested", "category": "", "is_disabled": false, "is_nsfw": false, "trait_offers_enabled": false, "collection_offers_enabled": true, "opensea_url": "https://opensea.io/collection/goblin-hood-3-fizzlewart", "project_url": "", "wiki_url": "", "discord_url": "", "telegram_url": "", "twitter_username": "", "instagram_username": "", "contracts": [{"address": "0x477db1bd8887d1537172f44818bf012b32b131ac", "chain": "ethereum"}]}, {"collection": "roses-152", "name": "Roses", "description": "Collection of works of art involving the genuine love story.", "image_url": "https://i.seadn.io/s/raw/files/ab39c5e0d4901b58e9f1e2ef20116d15.png?w=500&auto=format", "banner_image_url": "", "owner": "0x886acf601e965e73e95cb052c1c85d4ee7582f28", "safelist_status": "not_requested", "category": "art", "is_disabled": false, "is_nsfw": false, "trait_offers_enabled": false, "collection_offers_enabled": true, "opensea_url": "https://opensea.io/collection/roses-152", "project_url": "", "wiki_url": "", "discord_url": "", "telegram_url": "", "twitter_username": "", "instagram_username": "", "contracts": [{"address": "0x45dba9ae1cc8b42d5da2c3c3eceaee4d1e79d47e", "chain": "ethereum"}]}, {"collection": "monkey-1503", "name": "Monkey", "description": "", "image_url": "https://i.seadn.io/s/raw/files/9e88015da1a4593a7040b89dd5f4f743.png?w=500&auto=format", "banner_image_url": "", "owner": "0xfb82aad5f72e2306bf676a4c4deb73ae25268792", "safelist_status": "not_requested", "category": "", "is_disabled": false, "is_nsfw": false, "trait_offers_enabled": false, "collection_offers_enabled": true, "opensea_url": "https://opensea.io/collection/monkey-1503", "project_url": "", "wiki_url": "", "discord_url": "", "telegram_url": "", "twitter_username": "", "instagram_username": "", "contracts": [{"address": "0xa7c9948cdac8a405ae5ef312b95481c1a3f0c632", "chain": "ethereum"}]}, {"collection": "persian-pop-2", "name": "Persian Pop", "description": "", "image_url": "", "banner_image_url": "", "owner": "0x50bbb2b913f2fd8145353a4c9d34016cf949891c", "safelist_status": "not_requested", "category": "", "is_disabled": false, "is_nsfw": false, "trait_offers_enabled": false, "collection_offers_enabled": false, "opensea_url": "https://opensea.io/collection/persian-pop-2", "project_url": "", "wiki_url": "", "discord_url": "", "telegram_url": "", "twitter_username": "", "instagram_username": "", "contracts": [{"address": "0x6777757ca8f311deeba103864912c764494d30a6", "chain": "ethereum"}]}, {"collection": "furistic-alien-art", "name": "Furistic Alien Art", "description": "", "image_url": "https://i.seadn.io/s/raw/files/da2a70d9d09a21eb7f351d7c4c16a960.png?w=500&auto=format", "banner_image_url": "", "owner": "0x71b7d7fc159ae487c0f60955e371f331f7a7231e", "safelist_status": "not_requested", "category": "", "is_disabled": false, "is_nsfw": false, "trait_offers_enabled": false, "collection_offers_enabled": true, "opensea_url": "https://opensea.io/collection/furistic-alien-art", "project_url": "", "wiki_url": "", "discord_url": "", "telegram_url": "", "twitter_username": "", "instagram_username": "", "contracts": [{"address": "0xae92fef3674fe13d1b6a1e1d132782ff7a3eb248", "chain": "ethereum"}]}, {"collection": "chill-pixel-wolf-1", "name": "Chill Pixel Wolf", "description": "", "image_url": "https://i.seadn.io/s/raw/files/1c765945447dd6d54a8155db568a7350.jpg?w=500&auto=format", "banner_image_url": "", "owner": "0x6a94be6da81586013ccfcf630dcf9e0019b259e3", "safelist_status": "not_requested", "category": "", "is_disabled": false, "is_nsfw": false, "trait_offers_enabled": false, "collection_offers_enabled": true, "opensea_url": "https://opensea.io/collection/chill-pixel-wolf-1", "project_url": "", "wiki_url": "", "discord_url": "", "telegram_url": "", "twitter_username": "", "instagram_username": "", "contracts": [{"address": "0x9ed5966c9dc6cec7c2706cd05c433d5c07b43e40", "chain": "ethereum"}]}, {"collection": "romeu-the-cute-bear", "name": "Romeu the cute bear", "description": "", "image_url": "https://i.seadn.io/s/raw/files/03c4e1cf149164831e7786bcdb943997.jpg?w=500&auto=format", "banner_image_url": "", "owner": "0x699b38a7b98ced61188c5236a5022ec720fac000", "safelist_status": "not_requested", "category": "art", "is_disabled": false, "is_nsfw": false, "trait_offers_enabled": false, "collection_offers_enabled": true, "opensea_url": "https://opensea.io/collection/romeu-the-cute-bear", "project_url": "", "wiki_url": "", "discord_url": "", "telegram_url": "", "twitter_username": "", "instagram_username": "", "contracts": [{"address": "0x469b4e6dba27699f492ff74568116f1f74f65168", "chain": "ethereum"}]}, {"collection": "endless-love-8", "name": "Endless Love", "description": "Endless Love is a collection of unique NFTs that capture the essence of love in a cyberpunk world. Each artwork blends raw human emotion with neon-lit cityscapes, futuristic technology, and a sense of infinite connection beyond time and space.\n\nIn this collection, love is reimagined through the lens of a high-tech future\u2014where glowing holograms intertwine, digital souls find each other in the vastness of cyberspace, and passion burns as brightly as neon reflections on rain-soaked streets.\n\nEndless Love is more than just a tribute to romance; it\u2019s a fusion of heart and machine, reminding us that even in the most advanced worlds, love remains eternal.", "image_url": "https://i.seadn.io/s/raw/files/6bcd6c35d267842c0d6cde329bd138d3.jpg?w=500&auto=format", "banner_image_url": "", "owner": "0xc364859ed681cf5f0acb72daebd413e7eb529c44", "safelist_status": "not_requested", "category": "art", "is_disabled": false, "is_nsfw": false, "trait_offers_enabled": false, "collection_offers_enabled": true, "opensea_url": "https://opensea.io/collection/endless-love-8", "project_url": "", "wiki_url": "", "discord_url": "", "telegram_url": "", "twitter_username": "", "instagram_username": "", "contracts": [{"address": "0xcce27c5de19a20fef6db0ad2e0934cf8dfe9ffc8", "chain": "ethereum"}]}, {"collection": "persian-pop-1", "name": "Persian Pop", "description": "", "image_url": "", "banner_image_url": "", "owner": "0x50bbb2b913f2fd8145353a4c9d34016cf949891c", "safelist_status": "not_requested", "category": "", "is_disabled": false, "is_nsfw": false, "trait_offers_enabled": false, "collection_offers_enabled": false, "opensea_url": "https://opensea.io/collection/persian-pop-1", "project_url": "", "wiki_url": "", "discord_url": "", "telegram_url": "", "twitter_username": "", "instagram_username": "", "contracts": [{"address": "0x3564ba1baf13bbdd444ea12262057a26b247f7b0", "chain": "ethereum"}]}, {"collection": "che-za-biznes-ya-pridumal", "name": "che za biznes ya pridumal", "description": "\"Revolution in motion: Che za biznes ya pridumal \ud83d\ude80\ud83d\udcb0\"", "image_url": "https://i.seadn.io/s/raw/files/0fa78dc12d054c19dc36bb0014cc7c48.png?w=500&auto=format", "banner_image_url": "", "owner": "0x758c0976b04bc8de2a051bf3c1e8d2270e5c9fc6", "safelist_status": "not_requested", "category": "domain-names", "is_disabled": false, "is_nsfw": false, "trait_offers_enabled": false, "collection_offers_enabled": true, "opensea_url": "https://opensea.io/collection/che-za-biznes-ya-pridumal", "project_url": "", "wiki_url": "", "discord_url": "", "telegram_url": "", "twitter_username": "", "instagram_username": "", "contracts": [{"address": "0x08423fb3f35a04de5a880277e759c6271a93edb9", "chain": "ethereum"}]}, {"collection": "persian-pop", "name": "Persian Pop", "description": "", "image_url": "", "banner_image_url": "", "owner": "0x50bbb2b913f2fd8145353a4c9d34016cf949891c", "safelist_status": "not_requested", "category": "", "is_disabled": false, "is_nsfw": false, "trait_offers_enabled": false, "collection_offers_enabled": false, "opensea_url": "https://opensea.io/collection/persian-pop", "project_url": "", "wiki_url": "", "discord_url": "", "telegram_url": "", "twitter_username": "", "instagram_username": "", "contracts": [{"address": "0x28c6b5579586766aa3f85a04d827152307e829e2", "chain": "ethereum"}]}, {"collection": "latin-women-1", "name": "Latin Women", "description": "A story told, A story listened to. She says what she wants, she says what she's seen. She is the one who will speak today. ", "image_url": "https://i.seadn.io/s/raw/files/850c2c645a6889184d877a74776cbc37.jpg?w=500&auto=format", "banner_image_url": "", "owner": "0xbda6d5884e669d6dae59b3f3da77d8e4963b1bd5", "safelist_status": "not_requested", "category": "pfps", "is_disabled": false, "is_nsfw": false, "trait_offers_enabled": false, "collection_offers_enabled": true, "opensea_url": "https://opensea.io/collection/latin-women-1", "project_url": "", "wiki_url": "", "discord_url": "", "telegram_url": "", "twitter_username": "", "instagram_username": "", "contracts": [{"address": "0x3e390b833b4b7bfe5a81018547d8beac67b14ae4", "chain": "ethereum"}]}, {"collection": "confusion-30", "name": "Confusion", "description": "That feeling when you create your first NFT ", "image_url": "https://i.seadn.io/s/raw/files/470a0720637295673b9e59e87f0d6fcf.png?w=500&auto=format", "banner_image_url": "", "owner": "0xbb3eaa87e8057f84fd47c16d59dfbd20ab9b5b2f", "safelist_status": "not_requested", "category": "", "is_disabled": false, "is_nsfw": false, "trait_offers_enabled": false, "collection_offers_enabled": true, "opensea_url": "https://opensea.io/collection/confusion-30", "project_url": "", "wiki_url": "", "discord_url": "", "telegram_url": "", "twitter_username": "", "instagram_username": "", "contracts": [{"address": "0x394153fce38d3dc63bd0c87a70c1b4384388f51f", "chain": "ethereum"}]}, {"collection": "mynft-622", "name": "MyNFT", "description": "", "image_url": "", "banner_image_url": "", "owner": "0x2e193ad196ed32fc14c434bcd2b339fd8451fa2f", "safelist_status": "not_requested", "category": "", "is_disabled": false, "is_nsfw": false, "trait_offers_enabled": false, "collection_offers_enabled": true, "opensea_url": "https://opensea.io/collection/mynft-622", "project_url": "", "wiki_url": "", "discord_url": "", "telegram_url": "", "twitter_username": "", "instagram_username": "", "contracts": [{"address": "0x7c45958226d76ce19f372bae606f0c24a1601622", "chain": "ethereum"}]}, {"collection": "phantom-regalia", "name": "Phantom Regalia", "description": "", "image_url": "https://i.seadn.io/s/raw/files/8a0c8aaaab83336fae539bb2101ae34a.jpg?w=500&auto=format", "banner_image_url": "", "owner": "0x4f68c715035649694b677d8ff587dfd2a7f2941c", "safelist_status": "not_requested", "category": "", "is_disabled": false, "is_nsfw": false, "trait_offers_enabled": false, "collection_offers_enabled": true, "opensea_url": "https://opensea.io/collection/phantom-regalia", "project_url": "", "wiki_url": "", "discord_url": "", "telegram_url": "", "twitter_username": "", "instagram_username": "", "contracts": [{"address": "0x2e7600e574a939e934014a1ae9aca496093c3b3a", "chain": "ethereum"}]}, {"collection": "porter-19", "name": "Porter", "description": "", "image_url": "https://i.seadn.io/s/raw/files/23199a6bfc1011988bdb446ff6e8e0d2.jpg?w=500&auto=format", "banner_image_url": "", "owner": "0xcf22e69e3bace53ed4fa4d3eb080c13314dbb9d0", "safelist_status": "not_requested", "category": "", "is_disabled": false, "is_nsfw": false, "trait_offers_enabled": false, "collection_offers_enabled": false, "opensea_url": "https://opensea.io/collection/porter-19", "project_url": "", "wiki_url": "", "discord_url": "", "telegram_url": "", "twitter_username": "", "instagram_username": "", "contracts": [{"address": "0xe2ed295bc60cd325183a8deb856203e1d1a5433e", "chain": "ethereum"}]}, {"collection": "sneks-onchain", "name": "Sneks Onchain", "description": "", "image_url": "https://i.seadn.io/s/raw/files/a25cb5f5f962a3a3634aeb4a93ddd051.webp?w=500&auto=format", "banner_image_url": "", "owner": "0x6a311a44fe1cfd26063e04d183fcb66358106a5e", "safelist_status": "not_requested", "category": "", "is_disabled": false, "is_nsfw": false, "trait_offers_enabled": false, "collection_offers_enabled": true, "opensea_url": "https://opensea.io/collection/sneks-onchain", "project_url": "", "wiki_url": "", "discord_url": "", "telegram_url": "", "twitter_username": "", "instagram_username": "", "contracts": [{"address": "0x8fa9d4638e8d8eeb19b1d308ecba008705adefc3", "chain": "ethereum"}]}, {"collection": "life-1001", "name": "LIFE", "description": "", "image_url": "https://i.seadn.io/s/raw/files/c8d3254f8ac45802c69de8f2ee8d724d.jpg?w=500&auto=format", "banner_image_url": "", "owner": "0xae8d32b90f351070bf7f54d94e6a04762091750e", "safelist_status": "not_requested", "category": "", "is_disabled": false, "is_nsfw": false, "trait_offers_enabled": false, "collection_offers_enabled": true, "opensea_url": "https://opensea.io/collection/life-1001", "project_url": "", "wiki_url": "", "discord_url": "", "telegram_url": "", "twitter_username": "", "instagram_username": "", "contracts": [{"address": "0xc5c9fe3d9f02f66e29b6c128206ae408b909c654", "chain": "ethereum"}]}, {"collection": "gea-x-moon-base", "name": "Gea-X Moon Base", "description": "\"And then we emerged to see the stars again...\" D.A. ", "image_url": "https://i.seadn.io/s/raw/files/367540ef7512d064f97cd347c018c017.jpg?w=500&auto=format", "banner_image_url": "https://i.seadn.io/s/primary-drops/0x322a0e557f9e0c18e611c3aabbb4f94f7d5526ea/34312719:about:media:c6cef8f6-dec6-4363-9aa6-865c4fa98fe6.jpeg?w=500&auto=format", "owner": "0x43f168e339832901dc572bc3680665d30d03bcbf", "safelist_status": "not_requested", "category": "art", "is_disabled": false, "is_nsfw": false, "trait_offers_enabled": false, "collection_offers_enabled": true, "opensea_url": "https://opensea.io/collection/gea-x-moon-base", "project_url": "https://sgtraiart.com/", "wiki_url": "", "discord_url": "", "telegram_url": "", "twitter_username": "", "instagram_username": "", "contracts": [{"address": "0x322a0e557f9e0c18e611c3aabbb4f94f7d5526ea", "chain": "ethereum"}]}, {"collection": "snek-photography", "name": "Snek Photography", "description": "", "image_url": "https://i.seadn.io/s/raw/files/20972fb20090eabd28bf66637912bb3a.jpg?w=500&auto=format", "banner_image_url": "", "owner": "0x6a311a44fe1cfd26063e04d183fcb66358106a5e", "safelist_status": "not_requested", "category": "", "is_disabled": false, "is_nsfw": false, "trait_offers_enabled": false, "collection_offers_enabled": false, "opensea_url": "https://opensea.io/collection/snek-photography", "project_url": "", "wiki_url": "", "discord_url": "", "telegram_url": "", "twitter_username": "", "instagram_username": "", "contracts": [{"address": "0x4617b0fe1d081545376a64e5a04a2fb41f873a4d", "chain": "ethereum"}]}, {"collection": "steak-20", "name": "Steak", "description": "", "image_url": "https://i.seadn.io/s/raw/files/23199a6bfc1011988bdb446ff6e8e0d2.jpg?w=500&auto=format", "banner_image_url": "", "owner": "0x56cec8c3cfb45cc5f5d87dded0ea067985e1d012", "safelist_status": "not_requested", "category": "", "is_disabled": false, "is_nsfw": false, "trait_offers_enabled": false, "collection_offers_enabled": true, "opensea_url": "https://opensea.io/collection/steak-20", "project_url": "", "wiki_url": "", "discord_url": "", "telegram_url": "", "twitter_username": "", "instagram_username": "", "contracts": [{"address": "0x4da08ed4385d687a852bef0e0ad79653811c1ab9", "chain": "ethereum"}]}, {"collection": "flam-2", "name": "Flam", "description": "the queen.", "image_url": "https://i.seadn.io/s/raw/files/9de545485225b6e0615542fd461999c7.jpg?w=500&auto=format", "banner_image_url": "", "owner": "0xf0397ce40d79b4723b6ffd809204fcc55a4bdfd1", "safelist_status": "not_requested", "category": "", "is_disabled": false, "is_nsfw": false, "trait_offers_enabled": false, "collection_offers_enabled": true, "opensea_url": "https://opensea.io/collection/flam-2", "project_url": "", "wiki_url": "", "discord_url": "", "telegram_url": "", "twitter_username": "", "instagram_username": "", "contracts": [{"address": "0x157ff5f106797e8f48723db363b0f10eb6550653", "chain": "ethereum"}]}], "next": "LXBrPTM0MzEyNjcy"}